Metadata-Version: 2.1
Name: smock
Version: 0.2.13
Summary: Serverboards Mock library
Home-page: https://github.com/serverboards/smock
Author: David Moreno
Author-email: dmoreno@serverboards.io
License: Apache2
Keywords: testing,mock,mocking
Platform: UNKNOWN
